meta_matching_tool/__init__.py
meta_matching_tool/model.py
meta_matching_tool/utils.py
meta_matching_tool/data/graph.graphhml
meta_matching_tool/data/kegg.txt
meta_matching_tool-1.8.0.dist-info/LICENSE.txt
meta_matching_tool-1.8.0.dist-info/METADATA
meta_matching_tool-1.8.0.dist-info/WHEEL
meta_matching_tool-1.8.0.dist-info/top_level.txt
meta_matching_tool-1.8.0.dist-info/RECORD
